ftw/__init__.py
ftw/errors.py
ftw/http.py
ftw/logchecker.py
ftw/pytest_plugin.py
ftw/ruleset.py
ftw/testrunner.py
ftw/util.py
ftw/util/ironbee.py
ftw/util/public_suffix_list.dat
ftw/util/request_to_yaml.py
ftw/util/output/b00-01-normal.yaml
ftw/util/output/b01-01-query-string.yaml
ftw/util/output/b02-01-request-hostname-uri.yaml
ftw/util/output/b02-02-request-hostname-header.yaml
ftw/util/output/b03-01-header.yaml
ftw/util/output/b03-02-header-user-agent.yaml
ftw/util/output/b03-03-header-referer.yaml
ftw/util/output/b03-04-header-cookie.yaml
ftw/util/output/b03-05-header-authorization-username.yaml
ftw/util/output/b03-06-header-authorization-password.yaml
ftw/util/output/b04-01-request-filename.yaml
ftw/util/output/b05-01-request-method.yaml
ftw/util/output/b06-01-request-protocol.yaml
ftw/util/output/b07-01-trailing-header-cookie.yaml
ftw/util/output/b08-01-request-body-urlencoded-param-value.yaml
ftw/util/output/b08-02-request-body-urlencoded-param-name.yaml
ftw/util/output/b09-01-request-body-json.yaml
ftw/util/output/b10-01-multipart-preamble.yaml
ftw/util/output/b10-02-multipart-param-name.yaml
ftw/util/output/b10-03-multipart-param-filename.yaml
ftw/util/output/b10-04-multipart-file-contents.yaml
ftw/util/output/b10-05-multipart-epilogue.yaml
ftw/util/output/m00-01-normal.yaml
ftw/util/output/m01-01-invalid-separator.yaml
ftw/util/output/m01-02-invalid-separator.yaml
ftw/util/output/m02-01-invalid-parameter-name.yaml
ftw/util/output/m02-02-invalid-parameter-name.yaml
ftw/util/output/m03-01-multiple-boundaries.yaml
ftw/util/output/m03-02-multiple-boundaries.yaml
ftw/util/output/m03-03-multiple-boundaries.yaml
ftw/util/output/m03-04-multiple-boundaries.yaml
ftw/util/output/m04-whitespace-after-parameter-name.yaml
ftw/util/output/m05-whitespace-before-parameter-value.yaml
ftw/util/output/m06-whitespace-after-parameter-value.yaml
ftw/util/output/m07-01-special-chars-in-boundary.yaml
ftw/util/output/m07-02-special-chars-in-boundary.yaml
ftw-1.3.0.dist-info/LICENSE
ftw-1.3.0.dist-info/METADATA
ftw-1.3.0.dist-info/WHEEL
ftw-1.3.0.dist-info/entry_points.txt
ftw-1.3.0.dist-info/top_level.txt
ftw-1.3.0.dist-info/RECORD
