Metadata-Version: 2.1
Name: ftw
Version: 1.3.0
Summary: Framework for Testing WAFs
Home-page: https://github.com/coreruleset/ftw
Author: Chaim Sanders, Zack Allen
Author-email: zma4580@gmail.com, chaim.sanders@gmail.com
License: UNKNOWN
Project-URL: Bug Tracker, https://github.com/coreruleset/ftw/issues
Keywords: waf
Platform: UNKNOWN
Classifier: Programming Language :: Python :: 3
Classifier: License :: OSI Approved :: Apache Software License
Classifier: Operating System :: OS Independent
Classifier: Framework :: Pytest
Requires-Python: >=3.6
License-File: LICENSE
Requires-Dist: Brotli (==1.0.9)
Requires-Dist: IPy (==1.01)
Requires-Dist: PyYAML (==6.0)
Requires-Dist: pytest (==6.2.5)
Requires-Dist: python-dateutil (==2.8.2)
